setup.py
src/picctv/__init__.py
src/picctv/picctv.py
src/picctv/utils.py
src/picctv.egg-info/PKG-INFO
src/picctv.egg-info/SOURCES.txt
src/picctv.egg-info/dependency_links.txt
src/picctv.egg-info/entry_points.txt
src/picctv.egg-info/requires.txt
src/picctv.egg-info/top_level.txt
src/picctv.egg-info/zip-safe