Metadata-Version: 1.0
Name: picctv
Version: 0.1.2
Summary: CCTV for the RaspberryPi & Camera Module.
Home-page: https://github.com/richardasaurus/pi-cctv
Author: Richard O'Dwyer
Author-email: richard@richard.do
License: proprietary
Platform: UNKNOWN
